datatosk/__init__.py
datatosk/consts/__init__.py
datatosk/consts/output_types.py
datatosk/errors.py
datatosk/main.py
datatosk/py.typed
datatosk/sources/__init__.py
datatosk/sources/databases/__init__.py
datatosk/sources/databases/mongodb.py
datatosk/sources/databases/sql/__init__.py
datatosk/sources/databases/sql/google_big_query.py
datatosk/sources/databases/sql/mysql.py
datatosk/sources/databases/sql/sql_source.py
datatosk/sources/files.py
datatosk/sources/network.py
datatosk/sources/source.py
datatosk/types.py
datatosk-1.1.0.dist-info/LICENSE
datatosk-1.1.0.dist-info/WHEEL
datatosk-1.1.0.dist-info/METADATA
datatosk-1.1.0.dist-info/RECORD
